DScollection/SinglyCircularLL.py
DScollection/__init__.py
DScollection/doublyCirclularLL.py
DScollection/doublyLL.py
DScollection/linkedList.py
DScollection/stack.py
DScollection-0.0.8.dist-info/LICENCE.txt
DScollection-0.0.8.dist-info/METADATA
DScollection-0.0.8.dist-info/WHEEL
DScollection-0.0.8.dist-info/top_level.txt
DScollection-0.0.8.dist-info/RECORD
