Metadata-Version: 2.1
Name: DScollection
Version: 0.0.8
Summary: A basic implementation of some data structures
Author: Kishan Chauhan
Author-email: kishanchauhan2006.25@gmail.com
Keywords: data structures stack linked list
Classifier: Development Status :: 1 - Planning
Classifier: Intended Audience :: Developers
Classifier: Programming Language :: Python :: 3
Classifier: Operating System :: OS Independent
License-File: LICENCE.txt
